formality/__init__.py
formality-0.0.0.dist-info/DESCRIPTION.rst
formality-0.0.0.dist-info/METADATA
formality-0.0.0.dist-info/RECORD
formality-0.0.0.dist-info/WHEEL
formality-0.0.0.dist-info/metadata.json
formality-0.0.0.dist-info/top_level.txt
tests/__init__.py
tests/test_sample.py
