Metadata-Version: 2.0
Name: formality
Version: 0.0.0
Summary: mathematical expression manipulation engine
Home-page: https://github.com/uchchwhash/formality
Author: Imam Tashdid ul Alam
Author-email: imam.alam@gmail.com
License: UNKNOWN
Platform: UNKNOWN
Classifier: Development Status :: 2 - Pre-Alpha
Classifier: Programming Language :: Python
Classifier: Programming Language :: Python :: 3.5
